{
  "id": "70556f46-5a9d-41c2-8b8c-391b1d24b6a7",
  "title": "NoSQL concepts capsules",
  "names": "",
  "twitters": "",
  "websites": "",
  "abstract": "With the NoSQL buzz word being around these days, we use it quite frequently but we miss the basic concepts behind it. So, don't fall into the same hole again and use database as a data store without understanding the concepts behind. \r\n\r\nIn this session, I will give you the NoSQL concepts capsules that you will never forget and will help you choose the right one for you and use it effectively."
}