{
  "id": "b95768c3-8453-41a9-91dc-39b5ad47a322",
  "title": "The People's Revolution in Development",
  "names": "",
  "twitters": "",
  "websites": "",
  "abstract": "You may have all the technical skill in the world, but you're only as effective as your ability to influence and understand people. In this session, we will explore the human relationships that developers need to nail in order to be the most effective at their job. We'll cover some practical tips as well as enjoying some humour around people's behaviours and motivations."
}